{"v":4,"entries":{"introduction--docs":{"id":"introduction--docs","title":"Introduction","name":"Docs","importPath":"./src/global/stories/Intro.stories.mdx","type":"docs","tags":["stories-mdx","stories-mdx-docsOnly","docs"],"storiesImports":[]},"foundation-colors--docs":{"id":"foundation-colors--docs","title":"Foundation/Colors","name":"Docs","importPath":"./src/global/stories/foundation/Colors.stories.mdx","type":"docs","tags":["stories-mdx","stories-mdx-docsOnly","docs"],"storiesImports":[]},"foundation-spacings--docs":{"id":"foundation-spacings--docs","title":"Foundation/Spacings","name":"Docs","importPath":"./src/global/stories/foundation/Spacings.stories.mdx","type":"docs","tags":["stories-mdx","stories-mdx-docsOnly","docs"],"storiesImports":[]},"foundation-typography--docs":{"id":"foundation-typography--docs","title":"Foundation/Typography","name":"Docs","importPath":"./src/global/stories/foundation/Typo.stories.mdx","type":"docs","tags":["stories-mdx","stories-mdx-docsOnly","docs"],"storiesImports":[]},"components-ui-stencilbutton--docs":{"id":"components-ui-stencilbutton--docs","title":"Components/UI/StencilButton","name":"Docs","importPath":"./src/components/ui/stencil-button/stencil-button.stories.ts","type":"docs","tags":["autodocs","docs"],"storiesImports":[]},"components-ui-stencilbutton--default":{"type":"story","id":"components-ui-stencilbutton--default","name":"Default","title":"Components/UI/StencilButton","importPath":"./src/components/ui/stencil-button/stencil-button.stories.ts","tags":["autodocs","story"]}}}
